jupyter_doexport/__init__.py
jupyter_doexport/magic_convert.py
jupyter_doexport/templates/dofile/dofile.do.j2
jupyter_doexport/templates/dofile_output/dofile_output.do.j2
jupyter_doexport-0.3.9.dist-info/LICENSE
jupyter_doexport-0.3.9.dist-info/WHEEL
jupyter_doexport-0.3.9.dist-info/METADATA
jupyter_doexport-0.3.9.dist-info/RECORD
