Metadata-Version: 2.1
Name: jupyter-doexport
Version: 0.3.9
Summary: A package to convert jupyter notebooks to Stata do-files
Home-page: https://github.com/amichuda/jupyter-doexport
License: MIT
Author: Aleksandr Michuda
Author-email: amichuda@gmail.com
Requires-Python: >=3.9,<4.0
Classifier: License :: OSI Approved :: MIT License
Classifier: Programming Language :: Python :: 3
Classifier: Programming Language :: Python :: 3.9
Requires-Dist: nbconvert (>=6.3.0,<7.0.0)
